taretto/__init__.py
taretto/context.py
taretto-0.5.5.dist-info/LICENSE
taretto-0.5.5.dist-info/METADATA
taretto-0.5.5.dist-info/WHEEL
taretto-0.5.5.dist-info/top_level.txt
taretto-0.5.5.dist-info/RECORD
