Metadata-Version: 2.1
Name: taretto
Version: 0.5.5
Summary: tooling for testing, offering Web UI navigation and interaction
Home-page: https://github.com/RedHatQE/taretto
Author: RedHatQE
Author-email: psavage@redhat.com
Maintainer: Pete Savage
Maintainer-email: psavage@redhat.com
License: GPL
Keywords: Testing,Widget,Navigation
Platform: UNKNOWN
Classifier: Development Status :: 5 - Production/Stable
Classifier: Intended Audience :: Developers
Classifier: Natural Language :: English
Classifier: License :: OSI Approved :: Apache Software License
Classifier: Operating System :: OS Independent
Classifier: Programming Language :: Python
Classifier: Programming Language :: Python :: 2
Classifier: Programming Language :: Python :: 2.7
Classifier: Programming Language :: Python :: 3
Classifier: Programming Language :: Python :: 3.4
Classifier: Programming Language :: Python :: 3.5
Classifier: Programming Language :: Python :: 3.6
Classifier: Programming Language :: Python :: 3.7
Classifier: Programming Language :: Python :: Implementation :: CPython
Classifier: Programming Language :: Python :: Implementation :: PyPy
Classifier: Topic :: Software Development :: Libraries :: Python Modules
Requires-Dist: widgetastic.core
Requires-Dist: widgetastic.patternfly
Requires-Dist: navmazing
Requires-Dist: sentaku
Requires-Dist: apipkg
